pyexopods/LICENSE.txt
pyexopods/__init__.py
pyexopods-0.0.1.dist-info/METADATA
pyexopods-0.0.1.dist-info/WHEEL
pyexopods-0.0.1.dist-info/RECORD
